cddst
