Metadata-Version: 2.1
Name: cddst
Version: 0.0.6
Summary: UNKNOWN
Home-page: UNKNOWN
Author: BruceLong
Author-email: 18656170559@163.com
License: MIT Licence
Platform: any
